jijzeptlab/__marker__.c
jijzeptlab/_version.py
jijzeptlab/jijzeptlab.py
jijzeptlab/exception.py
jijzeptlab/__marker__.cpython-38-aarch64-linux-gnu.so
jijzeptlab/__init__.py
jijzeptlab/client.py
jijzeptlab/compile.py
jijzeptlab/sampler/da4.py
jijzeptlab/sampler/va.py
jijzeptlab/sampler/__init__.py
jijzeptlab/sampler/sa.py
jijzeptlab/sampler/dwaveleap.py
jijzeptlab/sampler/__pycache__/sa.cpython-38.pyc
jijzeptlab/sampler/__pycache__/dwaveleap.cpython-38.opt-1.pyc
jijzeptlab/sampler/__pycache__/va.cpython-38.pyc
jijzeptlab/sampler/__pycache__/va.cpython-38.opt-1.pyc
jijzeptlab/sampler/__pycache__/da4.cpython-38.pyc
jijzeptlab/sampler/__pycache__/dwaveleap.cpython-38.pyc
jijzeptlab/sampler/__pycache__/__init__.cpython-38.pyc
jijzeptlab/sampler/__pycache__/da4.cpython-38.opt-1.pyc
jijzeptlab/sampler/__pycache__/__init__.cpython-38.opt-1.pyc
jijzeptlab/sampler/__pycache__/sa.cpython-38.opt-1.pyc
jijzeptlab/__pycache__/jijzeptlab.cpython-38.opt-1.pyc
jijzeptlab/__pycache__/_version.cpython-38.opt-1.pyc
jijzeptlab/__pycache__/_version.cpython-38.pyc
jijzeptlab/__pycache__/client.cpython-38.pyc
jijzeptlab/__pycache__/compile.cpython-38.pyc
jijzeptlab/__pycache__/exception.cpython-38.pyc
jijzeptlab/__pycache__/client.cpython-38.opt-1.pyc
jijzeptlab/__pycache__/compile.cpython-38.opt-1.pyc
jijzeptlab/__pycache__/__init__.cpython-38.pyc
jijzeptlab/__pycache__/exception.cpython-38.opt-1.pyc
jijzeptlab/__pycache__/jijzeptlab.cpython-38.pyc
jijzeptlab/__pycache__/__init__.cpython-38.opt-1.pyc
jijzeptlab/solver/__init__.py
jijzeptlab/solver/nlp.py
jijzeptlab/solver/mip.py
jijzeptlab/solver/__pycache__/nlp.cpython-38.opt-1.pyc
jijzeptlab/solver/__pycache__/nlp.cpython-38.pyc
jijzeptlab/solver/__pycache__/__init__.cpython-38.pyc
jijzeptlab/solver/__pycache__/mip.cpython-38.opt-1.pyc
jijzeptlab/solver/__pycache__/mip.cpython-38.pyc
jijzeptlab/solver/__pycache__/__init__.cpython-38.opt-1.pyc
jijzeptlab/utils/baseclass.py
jijzeptlab_client-0.6.4.dist-info/METADATA
jijzeptlab_client-0.6.4.dist-info/top_level.txt
jijzeptlab_client-0.6.4.dist-info/WHEEL
jijzeptlab_client-0.6.4.dist-info/LICENSE.txt
jijzeptlab_client-0.6.4.dist-info/RECORD
