Metadata-Version: 2.1
Name: jijzeptlab-client
Version: 0.6.4
Summary: Python Interface for JijZeptLab.
Home-page: https://www.jijzept.com
Author: Jij Inc.
Author-email: info@j-ij.com
License: Other/Proprietary License
Project-URL: Documentation, https://www.documentation.jijzept.com
Project-URL: Reference, https://www.ref.documentation.jijzept.com
Project-URL: JijModeling, https://pypi.org/project/jijmodeling/
Classifier: Programming Language :: Python :: 3.9
Classifier: Programming Language :: Python :: 3.10
Classifier: Programming Language :: Python :: 3 :: Only
Classifier: Programming Language :: Python :: Implementation :: CPython
Classifier: Operating System :: Microsoft :: Windows
Classifier: Operating System :: POSIX
Classifier: Operating System :: MacOS
Requires-Python: <3.11,>=3.8
License-File: LICENSE.txt
Requires-Dist: jijzept <1.18.0,>=1.17.0
Requires-Dist: jijmodeling <2.0.0,>=1.0.0rc4
Requires-Dist: python-rapidjson <2.0,>=1.0
Requires-Dist: jijmodeling-transpiler <0.7.0,>=0.6.0rc3
Requires-Dist: protobuf <5.0,>=3.20
Requires-Dist: pydantic <3.0.0,>=2.0.0
